itarj_console.py
itarjconsole_app-1.0.0.dist-info/entry_points.txt
itarjconsole_app-1.0.0.dist-info/WHEEL
itarjconsole_app-1.0.0.dist-info/METADATA
itarjconsole_app-1.0.0.dist-info/RECORD
