Metadata-Version: 2.1
Name: itarjconsole-app
Version: 1.0.0
Summary: A console app that allows users to register fake job alerts and allows others to view those posts by searching for keywords.
Author: Onuh Chukwuma
Requires-Python: >=3.7,<4.0
Classifier: Programming Language :: Python :: 3
Classifier: Programming Language :: Python :: 3.7
Classifier: Programming Language :: Python :: 3.8
